qiplot/__init__.py
qiplot/arparser.py
qiplot/colors.py
qiplot/generate_testdata.py
qiplot/imageroi.py
qiplot/logconf.py
qiplot/plot1d.py
qiplot/plot2d.py
qiplot/reader.py
qiplot-1.1.6.dist-info/licenses/LICENSE
qiplot-1.1.6.dist-info/METADATA
qiplot-1.1.6.dist-info/WHEEL
qiplot-1.1.6.dist-info/entry_points.txt
qiplot-1.1.6.dist-info/top_level.txt
qiplot-1.1.6.dist-info/RECORD
