Metadata-Version: 2.4
Name: qiplot
Version: 1.1.6
Summary: Graphs in 1D and 2D
Maintainer: steche
License: MIT
License-File: LICENSE
Dynamic: description-content-type
Dynamic: license
Dynamic: license-file
Dynamic: maintainer
Dynamic: summary
